terminal_tracker/__init__.py
terminal_tracker/__main__.py
terminal_tracker/_version.py
terminal_tracker/argparser.py
terminal_tracker/export.py
terminal_tracker/frequency.py
terminal_tracker/preprocess.py
terminal_tracker/searching.py
terminal_tracker/tag.py
terminal_tracker/time.py
terminal_tracker/timeanalysis.py
terminal_tracker/configs/configuring_bash.sh
terminal_tracker/configs/configuring_zsh.sh
terminal_tracker/examples/Frequency.ipynb
terminal_tracker/examples/Searching.ipynb
terminal_tracker/examples/TagTime.ipynb
terminal_tracker/examples/example.ipynb
terminal_tracker/history_files/bash_history.txt
terminal_tracker/history_files/bash_history_timeframe.txt
terminal_tracker/history_files/storing_histfiles.sh
terminal_tracker/history_files/zsh_history.txt
terminal_tracker/history_files/zsh_history_timeframe.txt
terminal_tracker/tests/test_export.py
terminal_tracker/tests/test_frequency.py
terminal_tracker/tests/test_integration.py
terminal_tracker/tests/test_preprocess.py
terminal_tracker/tests/test_searching.py
terminal_tracker/tests/test_tag.py
terminal_tracker/tests/test_timeanalysis.py
terminal_tracker/tests/test_unit.py
terminal_tracker/tests/zsh_test.txt
terminal_tracker-1.0.0.dist-info/LICENSE
terminal_tracker-1.0.0.dist-info/METADATA
terminal_tracker-1.0.0.dist-info/WHEEL
terminal_tracker-1.0.0.dist-info/top_level.txt
terminal_tracker-1.0.0.dist-info/RECORD
